coec_llmhub-0.1.4.dist-info/licenses/LICENSE
llmhub/main.py
llmhub/core/__init__.py
llmhub/core/llms/__init__.py
llmhub/core/llms/anthropic/__init__.py
llmhub/core/llms/anthropic/client.py
llmhub/core/llms/gemini/__init__.py
llmhub/core/llms/gemini/batch.py
llmhub/core/llms/gemini/client.py
llmhub/core/llms/gemini/response.py
llmhub/core/llms/template/__init__.py
llmhub/core/llms/template/batch.py
llmhub/core/llms/template/client.py
llmhub/core/llms/template/exceptions.py
llmhub/core/llms/template/response.py
llmhub/core/secret_managers/__init__.py
llmhub/core/secret_managers/alibaba_secrets_manager.py
llmhub/core/secret_managers/aws_secret_manager.py
llmhub/core/secret_managers/azure_key_vault.py
llmhub/core/secret_managers/base.py
llmhub/core/secret_managers/cloudflare_secrets_store.py
llmhub/core/secret_managers/digitalocean_secrets.py
llmhub/core/secret_managers/env_var_secrets.py
llmhub/core/secret_managers/google_secret_manager.py
llmhub/core/secret_managers/hashicorp_vault.py
llmhub/core/secret_managers/ibm_secrets_manager.py
llmhub/core/secret_managers/oracle_vault.py
llmhub/core/vector_stores/__init__.py
llmhub/services/agent/__init__.py
llmhub/services/agent/memory/__init__.py
llmhub/services/chat/__init__.py
llmhub/services/rag/__init__.py
llmhub/services/rag/base.py
llmhub/services/rag/chunk/__init__.py
coec_llmhub-0.1.4.dist-info/METADATA
coec_llmhub-0.1.4.dist-info/WHEEL
coec_llmhub-0.1.4.dist-info/top_level.txt
coec_llmhub-0.1.4.dist-info/RECORD
