Metadata-Version: 2.4
Name: coec-llmhub
Version: 0.1.4
Summary: Add your description here
Requires-Python: >=3.13
License-File: LICENSE
Requires-Dist: httpx>=0.28.1
Requires-Dist: python-magic>=0.4.27
Dynamic: license-file
